Implementação em FPGA/CodeGenerated/DE2_115/FPGA_Urna/Urna_module.v
module Urna_module(C1,C2,C3,C4,Nulo,Clock,Digit,Valid,Finish,StatusValido,StatusNulo,Next);
  input wire Clock,Valid,Finish,Next;
  input wire [3:0]Digit;
  output reg [7:0]Nulo = 8'b00000000;
  output reg [7:0]C1 = 8'b00000000;
  output reg [7:0]C2 = 8'b00000000;
  output reg [7:0]C3 = 8'b00000000;
  output reg [7:0]C4 = 8'b00000000;
  output reg StatusValido = 0;
  output reg StatusNulo = 1;
  reg [3:0]Estado = 4'b0000;

always @ (posedge Clock) begin
    if((~Finish * ~Next))begin
        case (Estado)
          4'b0000: //E0
            begin
              if((Digit[3]==0)&(Digit[2]==0)&(Digit[1]==1)&(Digit[0]==1)&(Valid))begin  //3
                 Estado <= 4'b0001;
              end
              else if(Valid)begin
                  Estado <= 4'b1000;
              end
            end

          4'b0001: //E1
            begin
              if((Digit[3]==0)&(Digit[2]==1)&(Digit[1]==0)&(Digit[0]==0)&(Valid))begin    //4
                 Estado <= 4'b0010;
              end
              else if((Digit[3]==0)&(Digit[2]==1)&(Digit[1]==0)&(Digit[0]==1)&(Valid))begin   //5
                 Estado <= 4'b0011;
              end
              else if(Valid)begin
                  Estado <= 4'b1000;
              end
            end

          4'b0010: //E2
            begin
              if((Digit[3]==1)&(Digit[2]==0)&(Digit[1]==0)&(Digit[0]==1)&(Valid))begin   //9
                 Estado <= 4'b0100;
              end
              else if((Digit[3]==1)&(Digit[2]==0)&(Digit[1]==0)&(Digit[0]==0)&(Valid))begin   //8
                 Estado <= 4'b0101;
              end
              else if((Digit[3]==0)&(Digit[2]==1)&(Digit[1]==1)&(Digit[0]==1)&(Valid))begin   //7
                 Estado <= 4'b0110;
              end
              else if(Valid)begin
                  Estado <= 4'b1000;
              end
            end

          4'b0011: //E3
            begin
              if((Digit[3]==0)&(Digit[2]==0)&(Digit[1]==0)&(Digit[0]==0)&(Valid))begin    //0
                 Estado <= 4'b0111;
              end
              else if(Valid)begin
                  Estado <= 4'b1000;
              end
            end

        //////////////////////////////////////Votos Begin --->>>>>>>>

          4'b0100: //E4
            begin
              if((Digit[3]==0)&(Digit[2]==1)&(Digit[1]==0)&(Digit[0]==0)&(Valid))begin    //4
                 C1 <= C1 + 8'b00000001;       //Voto no Samuel-3494
                 StatusValido <= 1;
					       Estado <= 4'b1001;
              end
              else if(Valid)begin
                  Estado <= 4'b1000;
              end
            end

          4'b0101: //E5
            begin
              if((Digit[3]==0)&(Digit[2]==1)&(Digit[1]==0)&(Digit[0]==1)&(Valid))begin    //5
                C2 <= C2 + 8'b00000001;       //Voto no Yuri-3485
                StatusValido <= 1;
					      Estado <= 4'b1001;
              end
              else if(Valid)begin
                  Estado <= 4'b1000;
              end
            end

          4'b0110: //E6
            begin
              if((Digit[3]==0)&(Digit[2]==0)&(Digit[1]==1)&(Digit[0]==0)&(Valid))begin    //2
                C3 <= C3 + 8'b00000001;       //Voto no William-3472
                StatusValido <= 1;
					      Estado <= 4'b1001;
              end
              else if(Valid)begin
                  Estado <= 4'b1000;
              end
            end

          4'b0111: //E7
            begin
              if((Digit[3]==0)&(Digit[2]==1)&(Digit[1]==0)&(Digit[0]==0)&(Valid))begin   //4
                C4 <= C4 + 8'b00000001;       //Voto no Marcos-3504
                StatusValido <= 1;
					      Estado <= 4'b1001;
              end
              else if(Valid)begin
                  Estado <= 4'b1000;
              end
            end
      	  4'b1000: //E8
            begin           //Voto nulo.
              Nulo <= Nulo + 8'b00000001;
              StatusNulo <= 0;
				      Estado <= 4'b1001;
            end
  			  4'b1001: //E9 Estado vazio
    				begin
    				end
        endcase
    end
    if(Next) begin
        StatusValido <= 0;
        StatusNulo <= 1;
        Estado <= 4'b0000;
    end
    if (Finish) begin
        StatusValido <= 0;
        StatusNulo <= 1;
        Nulo <= 8'b00000000;
        C1 <= 8'b00000000;
        C2 <= 8'b00000000;
        C3 <= 8'b00000000;
        C4 <= 8'b00000000;
        Estado <= 4'b0000;
    end
end
endmodule

testbench.v
`include "Urna_module.v"
module testbench();
  reg Valid, Finish, Clock, Next;
  reg [3:0]Digit;
  wire [7:0]Nulo;
  wire [7:0]C1;
  wire [7:0]C2;
  wire [7:0]C3;
  wire [7:0]C4;
  wire StatusValido,StatusNulo;
  Urna_module UrnaAUX(.C1(C1),.C2(C2),.C3(C3),.C4(C4),.Nulo(Nulo),.Clock(Clock),.Digit(Digit),.Valid(Valid),.Next(Next),.StatusValido(StatusValido),.StatusNulo(StatusNulo), .Finish(Finish));
  always
    #1 Clock <= ~Clock;
  initial begin
    $dumpfile("testdump.vcd");
    $dumpvars(0, testbench);
    $display("Testbech da Urna Eletronica iniciado!");
    $monitor("Novo voto detectado! \nC1:  %d\nC2:  %d\nC3:  %d\nC4:  %d\nNulo:%d\n", C1, C2, C3, C4, Nulo);
  end
  initial begin
    Clock = 0;
    Digit = 4'b0000;
    Valid = 0;
    Finish = 0;
    Next = 0;
//Reset e Finish
    #1 Next = 1;
    #1 Next = 0;

//Voto Samuel
    #2 Valid = 1;
    #1 Digit = 4'b0011;
    #1 Valid = 0;


    #2 Valid = 1;
    #1 Digit = 4'b0100;
    #1 Valid = 0;


    #2 Valid = 1;
    #1 Digit = 4'b1001;
    #1 Valid = 0;


    #2 Valid = 1;
    #1 Digit = 4'b0100;
    #1 Valid = 0;
/////////////////////////////////////
//Reset e Finish
    #1 Next = 1;
    #1 Next = 0;
//Voto Yuri
    #2 Valid = 1;
    #1 Digit = 4'b0011;
    #1 Valid = 0;


    #2 Valid = 1;
    #1 Digit = 4'b0100;
    #1 Valid = 0;


    #2 Valid = 1;
    #1 Digit = 4'b1000;
    #1 Valid = 0;


    #2 Valid = 1;
    #1 Digit = 4'b0101;
    #1 Valid = 0;
///////////////////////////////////////
//Reset e Finish
    #1 Next = 1;
    #1 Next = 0;
//Voto Samuel
    #2 Valid = 1;
    #1 Digit = 4'b0011;
    #1 Valid = 0;


    #2 Valid = 1;
    #1 Digit = 4'b0100;
    #1 Valid = 0;                             ////Segundo voto para samuel


    #2 Valid = 1;
    #1 Digit = 4'b1001;
    #1 Valid = 0;


    #2 Valid = 1;
    #1 Digit = 4'b0100;
    #1 Valid = 0;
/////////////////////////////////////
//Reset e Finish
    #1 Next = 1;
    #1 Next = 0;
//Voto William
    #2 Valid = 1;
    #1 Digit = 4'b0011;
    #1 Valid = 0;


    #2 Valid = 1;
    #1 Digit = 4'b0100;
    #1 Valid = 0;


    #2 Valid = 1;
    #1 Digit = 4'b0111;
    #1 Valid = 0;


    #2 Valid = 1;
    #1 Digit = 4'b0010;
    #1 Valid = 0;
/////////////////////////////////////
//Reset e Finish
    #1 Next = 1;
    #1 Next = 0;
//Voto Marcos
    #2 Valid = 1;
    #1 Digit = 4'b0011;
    #1 Valid = 0;


    #2 Valid = 1;
    #1 Digit = 4'b0101;
    #1 Valid = 0;


    #2 Valid = 1;
    #1 Digit = 4'b0000;
    #1 Valid = 0;


    #2 Valid = 1;
    #1 Digit = 4'b0100;
    #1 Valid = 0;
///////////////////////////////////
//Reset e Finish
    #1 Next = 1;
    #1 Next = 0;


//Voto Nulo
    #2 Valid = 1;
    #1 Digit = 4'b0011;
    #1 Valid = 0;
    #2 Valid = 1;



    #1 Digit = 4'b0000;
    #1 Valid = 0;
    #2 Valid = 1;

///////////////////////////////////
//Reset e Finish
    #1 Finish = 1;
    #1 Finish = 0;

    $finish;
  end
endmodule

testdump.vcd
$date
	Wed Nov 28 10:29:37 2018
$end
$version
	Icarus Verilog
$end
$timescale
	1s
$end
$scope module testbench $end
$var wire 1 ! StatusValido $end
$var wire 1 " StatusNulo $end
$var wire 8 # Nulo [7:0] $end
$var wire 8 $ C4 [7:0] $end
$var wire 8 % C3 [7:0] $end
$var wire 8 & C2 [7:0] $end
$var wire 8 ' C1 [7:0] $end
$var reg 1 ( Clock $end
$var reg 4 ) Digit [3:0] $end
$var reg 1 * Finish $end
$var reg 1 + Next $end
$var reg 1 , Valid $end
$scope module UrnaAUX $end
$var wire 1 ( Clock $end
$var wire 4 - Digit [3:0] $end
$var wire 1 * Finish $end
$var wire 1 + Next $end
$var wire 1 , Valid $end
$var reg 8 . C1 [7:0] $end
$var reg 8 / C2 [7:0] $end
$var reg 8 0 C3 [7:0] $end
$var reg 8 1 C4 [7:0] $end
$var reg 4 2 Estado [3:0] $end
$var reg 8 3 Nulo [7:0] $end
$var reg 1 " StatusNulo $end
$var reg 1 ! StatusValido $end
$upscope $end
$upscope $end
$enddefinitions $end
#0
$dumpvars
b0 3
b0 2
b0 1
b0 0
b0 /
b0 .
b0 -
0,
0+
0*
b0 )
0(
b0 '
b0 &
b0 %
b0 $
b0 #
1"
0!
$end
#1
1(
1+
#2
0(
0+
#3
1(
#4
0(
1,
#5
b1 2
1(
b11 )
b11 -
#6
0(
0,
#7
1(
#8
0(
1,
#9
b10 2
1(
b100 )
b100 -
#10
0(
0,
#11
1(
#12
0(
1,
#13
b100 2
1(
b1001 )
b1001 -
#14
0(
0,
#15
1(
#16
0(
1,
#17
b1001 2
1!
b1 '
b1 .
1(
b100 )
b100 -
#18
0(
0,
#19
b0 2
0!
1(
1+
#20
0(
0+
#21
1(
#22
0(
1,
#23
b1 2
1(
b11 )
b11 -
#24
0(
0,
#25
1(
#26
0(
1,
#27
b10 2
1(
b100 )
b100 -
#28
0(
0,
#29
1(
#30
0(
1,
#31
b101 2
1(
b1000 )
b1000 -
#32
0(
0,
#33
1(
#34
0(
1,
#35
b1001 2
1!
b1 &
b1 /
1(
b101 )
b101 -
#36
0(
0,
#37
b0 2
0!
1(
1+
#38
0(
0+
#39
1(
#40
0(
1,
#41
b1 2
1(
b11 )
b11 -
#42
0(
0,
#43
1(
#44
0(
1,
#45
b10 2
1(
b100 )
b100 -
#46
0(
0,
#47
1(
#48
0(
1,
#49
b100 2
1(
b1001 )
b1001 -
#50
0(
0,
#51
1(
#52
0(
1,
#53
b1001 2
1!
b10 '
b10 .
1(
b100 )
b100 -
#54
0(
0,
#55
b0 2
0!
1(
1+
#56
0(
0+
#57
1(
#58
0(
1,
#59
b1 2
1(
b11 )
b11 -
#60
0(
0,
#61
1(
#62
0(
1,
#63
b10 2
1(
b100 )
b100 -
#64
0(
0,
#65
1(
#66
0(
1,
#67
b110 2
1(
b111 )
b111 -
#68
0(
0,
#69
1(
#70
0(
1,
#71
b1001 2
1!
b1 %
b1 0
1(
b10 )
b10 -
#72
0(
0,
#73
b0 2
0!
1(
1+
#74
0(
0+
#75
1(
#76
0(
1,
#77
b1 2
1(
b11 )
b11 -
#78
0(
0,
#79
1(
#80
0(
1,
#81
b11 2
1(
b101 )
b101 -
#82
0(
0,
#83
1(
#84
0(
1,
#85
b111 2
1(
b0 )
b0 -
#86
0(
0,
#87
1(
#88
0(
1,
#89
b1001 2
1!
b1 $
b1 1
1(
b100 )
b100 -
#90
0(
0,
#91
b0 2
0!
1(
1+
#92
0(
0+
#93
1(
#94
0(
1,
#95
b1 2
1(
b11 )
b11 -
#96
0(
0,
#97
1(
#98
0(
1,
#99
b1000 2
1(
b0 )
b0 -
#100
0(
0,
#101
b1001 2
0"
b1 #
b1 3
1(
#102
0(
1,
#103
b0 2
b0 $
b0 1
b0 %
b0 0
b0 &
b0 /
b0 '
b0 .
b0 #
b0 3
1"
1(
1*
#104
0(
0*
